{
  "fetchedAt": "2026-07-21T21:23:02.172Z",
  "entries": {
    "arsenal-fc": {
      "primaryHex": "#EF0107",
      "secondaryHex": "#DB0007",
      "accentHex": "#9C824A",
      "allHex": [
        "#EF0107",
        "#DB0007",
        "#9C824A",
        "#023474",
        "#FFFFFF"
      ],
      "rgb": [
        "rgb(239, 1, 7)",
        "rgb(219, 0, 7)",
        "rgb(156, 130, 74)",
        "rgb(2, 52, 116)",
        "rgb(255, 255, 255)"
      ],
      "cmyk": [
        "cmyk(0%, 100%, 97%, 6%)",
        "cmyk(0%, 100%, 97%, 14%)",
        "cmyk(0%, 17%, 53%, 39%)",
        "cmyk(98%, 55%, 0%, 55%)",
        "cmyk(0%, 0%, 0%, 0%)"
      ]
    },
    "chelsea-fc": {
      "primaryHex": "#001489",
      "secondaryHex": "#FFFFFF",
      "accentHex": "#FF0000",
      "allHex": [
        "#001489",
        "#FFFFFF",
        "#FF0000",
        "#DBA111",
        "#D1D3D4",
        "#6A7AB5"
      ],
      "rgb": [
        "rgb(0, 20, 137)",
        "rgb(255, 255, 255)",
        "rgb(255, 0, 0)",
        "rgb(219, 161, 17)",
        "rgb(209, 211, 212)",
        "rgb(106, 122, 181)"
      ],
      "cmyk": [
        "cmyk(100%, 85%, 0%, 46%)",
        "cmyk(0%, 0%, 0%, 0%)",
        "cmyk(0%, 100%, 100%, 0%)",
        "cmyk(0%, 26%, 92%, 14%)",
        "cmyk(1%, 0%, 0%, 17%)",
        "cmyk(41%, 33%, 0%, 29%)"
      ]
    },
    "everton-fc": {
      "primaryHex": "#00009E",
      "secondaryHex": "#FFFFFF",
      "accentHex": null,
      "allHex": [
        "#00009E",
        "#FFFFFF"
      ],
      "rgb": [
        "rgb(0, 0, 158)",
        "rgb(255, 255, 255)"
      ],
      "cmyk": [
        "cmyk(100%, 100%, 0%, 38%)",
        "cmyk(0%, 0%, 0%, 0%)"
      ]
    },
    "fulham-fc": {
      "primaryHex": "#CC0000",
      "secondaryHex": "#FFFFFF",
      "accentHex": "#000000",
      "allHex": [
        "#CC0000",
        "#FFFFFF",
        "#000000"
      ],
      "rgb": [
        "rgb(204, 0, 0)",
        "rgb(255, 255, 255)",
        "rgb(0, 0, 0)"
      ],
      "cmyk": [
        "cmyk(0%, 100%, 100%, 20%)",
        "cmyk(0%, 0%, 0%, 0%)",
        "cmyk(0%, 0%, 0%, 100%)"
      ]
    },
    "liverpool-fc": {
      "primaryHex": "#E51C25",
      "secondaryHex": null,
      "accentHex": null,
      "allHex": [
        "#E51C25"
      ],
      "rgb": [
        "rgb(229, 28, 37)"
      ],
      "cmyk": [
        "cmyk(0%, 88%, 84%, 10%)"
      ]
    },
    "manchester-city-fc": {
      "primaryHex": "#6CADDF",
      "secondaryHex": "#00285E",
      "accentHex": "#FFC758",
      "allHex": [
        "#6CADDF",
        "#00285E",
        "#FFC758",
        "#D4A11E",
        "#EE3124",
        "#FFFFFF"
      ],
      "rgb": [
        "rgb(108, 173, 223)",
        "rgb(0, 40, 94)",
        "rgb(255, 199, 88)",
        "rgb(212, 161, 30)",
        "rgb(238, 49, 36)",
        "rgb(255, 255, 255)"
      ],
      "cmyk": [
        "cmyk(52%, 22%, 0%, 13%)",
        "cmyk(100%, 57%, 0%, 63%)",
        "cmyk(0%, 22%, 65%, 0%)",
        "cmyk(0%, 24%, 86%, 17%)",
        "cmyk(0%, 79%, 85%, 7%)",
        "cmyk(0%, 0%, 0%, 0%)"
      ]
    },
    "manchester-united-fc": {
      "primaryHex": "#C1040B",
      "secondaryHex": "#FFE500",
      "accentHex": "#DA020E",
      "allHex": [
        "#C1040B",
        "#FFE500",
        "#DA020E",
        "#000000"
      ],
      "rgb": [],
      "cmyk": []
    },
    "newcastle-united-fc": {
      "primaryHex": "#231F20",
      "secondaryHex": "#FFFFFF",
      "accentHex": "#BBBDBF",
      "allHex": [
        "#231F20",
        "#FFFFFF",
        "#BBBDBF",
        "#F0B83D",
        "#00B6F1",
        "#EF3E2E"
      ],
      "rgb": [
        "rgb(35, 31, 32)",
        "rgb(255, 255, 255)",
        "rgb(187, 189, 191)",
        "rgb(240, 184, 61)",
        "rgb(0, 182, 241)",
        "rgb(239, 62, 46)"
      ],
      "cmyk": [
        "cmyk(0%, 11%, 9%, 86%)",
        "cmyk(0%, 0%, 0%, 0%)",
        "cmyk(2%, 1%, 0%, 25%)",
        "cmyk(0%, 23%, 75%, 6%)",
        "cmyk(100%, 24%, 0%, 5%)",
        "cmyk(0%, 74%, 81%, 6%)"
      ]
    },
    "tottenham-hotspur-fc": {
      "primaryHex": "#132257",
      "secondaryHex": null,
      "accentHex": null,
      "allHex": [
        "#132257"
      ],
      "rgb": [
        "rgb(19, 34, 87)"
      ],
      "cmyk": [
        "cmyk(78%, 61%, 0%, 66%)"
      ]
    },
    "leeds-united-fc": {
      "primaryHex": "#FFE003",
      "secondaryHex": "#0060A9",
      "accentHex": "#FFFFFF",
      "allHex": [
        "#FFE003",
        "#0060A9",
        "#FFFFFF"
      ],
      "rgb": [
        "rgb(255, 224, 3)",
        "rgb(0, 96, 169)",
        "rgb(255, 255, 255)"
      ],
      "cmyk": [
        "cmyk(0%, 12%, 99%, 0%)",
        "cmyk(100%, 43%, 0%, 34%)",
        "cmyk(0%, 0%, 0%, 0%)"
      ]
    },
    "nottingham-forest-fc": {
      "primaryHex": "#DD0000",
      "secondaryHex": null,
      "accentHex": null,
      "allHex": [
        "#DD0000"
      ],
      "rgb": [
        "rgb(221, 0, 0)"
      ],
      "cmyk": [
        "cmyk(0%, 100%, 100%, 13%)"
      ]
    },
    "crystal-palace-fc": {
      "primaryHex": "#0055A5",
      "secondaryHex": "#FFFFFF",
      "accentHex": "#EE2E24",
      "allHex": [
        "#0055A5",
        "#FFFFFF",
        "#EE2E24",
        "#B7B7B7",
        "#E4E4E4"
      ],
      "rgb": [
        "rgb(0, 85, 165)",
        "rgb(255, 255, 255)",
        "rgb(238, 46, 36)",
        "rgb(183, 183, 183)",
        "rgb(228, 228, 228)"
      ],
      "cmyk": [
        "cmyk(100%, 48%, 0%, 35%)",
        "cmyk(0%, 0%, 0%, 0%)",
        "cmyk(0%, 81%, 85%, 7%)",
        "cmyk(0%, 0%, 0%, 28%)",
        "cmyk(0%, 0%, 0%, 11%)"
      ]
    },
    "brentford-fc": {
      "primaryHex": "#E30613",
      "secondaryHex": "#FBB800",
      "accentHex": "#FFFFFF",
      "allHex": [
        "#E30613",
        "#FBB800",
        "#FFFFFF",
        "#140E0C",
        "#E8E4D9"
      ],
      "rgb": [
        "rgb(227, 6, 19)",
        "rgb(251, 184, 0)",
        "rgb(255, 255, 255)",
        "rgb(20, 14, 12)",
        "rgb(232, 228, 217)"
      ],
      "cmyk": [
        "cmyk(0%, 97%, 92%, 11%)",
        "cmyk(0%, 27%, 100%, 2%)",
        "cmyk(0%, 0%, 0%, 0%)",
        "cmyk(0%, 30%, 40%, 92%)",
        "cmyk(0%, 2%, 6%, 9%)"
      ]
    },
    "club-atletico-de-madrid": {
      "primaryHex": "#282A6F",
      "secondaryHex": "#E8151E",
      "accentHex": "#FFFFFF",
      "allHex": [
        "#282A6F",
        "#E8151E",
        "#FFFFFF",
        "#000000",
        "#7E4F3A",
        "#006A3F"
      ],
      "rgb": [
        "rgb(40, 42, 111)",
        "rgb(232, 21, 30)",
        "rgb(255, 255, 255)",
        "rgb(0, 0, 0)",
        "rgb(126, 79, 58)",
        "rgb(0, 106, 63)"
      ],
      "cmyk": [
        "cmyk(64%, 62%, 0%, 56%)",
        "cmyk(0%, 91%, 87%, 9%)",
        "cmyk(0%, 0%, 0%, 0%)",
        "cmyk(0%, 0%, 0%, 100%)",
        "cmyk(0%, 37%, 54%, 51%)",
        "cmyk(100%, 0%, 41%, 58%)"
      ]
    },
    "ca-osasuna": {
      "primaryHex": "#CB2725",
      "secondaryHex": "#2C1A69",
      "accentHex": "#AB842C",
      "allHex": [
        "#CB2725",
        "#2C1A69",
        "#AB842C",
        "#FFFFFF"
      ],
      "rgb": [
        "rgb(203, 39, 37)",
        "rgb(44, 26, 105)",
        "rgb(171, 132, 44)",
        "rgb(255, 255, 255)"
      ],
      "cmyk": [
        "cmyk(0%, 81%, 82%, 20%)",
        "cmyk(58%, 75%, 0%, 59%)",
        "cmyk(0%, 23%, 74%, 33%)",
        "cmyk(0%, 0%, 0%, 0%)"
      ]
    },
    "fc-barcelona": {
      "primaryHex": "#A50044",
      "secondaryHex": "#004D98",
      "accentHex": "#EDBB00",
      "allHex": [
        "#A50044",
        "#004D98",
        "#EDBB00",
        "#DB0030",
        "#FFED02",
        "#FFFFFF"
      ],
      "rgb": [],
      "cmyk": []
    },
    "real-madrid-cf": {
      "primaryHex": "#FEBE10",
      "secondaryHex": "#00529F",
      "accentHex": "#FFFFFF",
      "allHex": [
        "#FEBE10",
        "#00529F",
        "#FFFFFF",
        "#EE324E"
      ],
      "rgb": [
        "rgb(254, 190, 16)",
        "rgb(0, 82, 159)",
        "rgb(255, 255, 255)",
        "rgb(238, 50, 78)"
      ],
      "cmyk": [
        "cmyk(0%, 25%, 94%, 0%)",
        "cmyk(100%, 48%, 0%, 38%)",
        "cmyk(0%, 0%, 0%, 0%)",
        "cmyk(0%, 79%, 67%, 7%)"
      ]
    },
    "rayo-vallecano-de-madrid": {
      "primaryHex": "#E3361D",
      "secondaryHex": "#C0AE33",
      "accentHex": "#251900",
      "allHex": [
        "#E3361D",
        "#C0AE33",
        "#251900",
        "#FFFFFF",
        "#008A3A"
      ],
      "rgb": [
        "rgb(227, 54, 29)",
        "rgb(192, 174, 51)",
        "rgb(37, 25, 0)",
        "rgb(255, 255, 255)",
        "rgb(0, 138, 58)"
      ],
      "cmyk": [
        "cmyk(0%, 76%, 87%, 11%)",
        "cmyk(0%, 9%, 73%, 25%)",
        "cmyk(0%, 32%, 100%, 85%)",
        "cmyk(0%, 0%, 0%, 0%)",
        "cmyk(100%, 0%, 58%, 46%)"
      ]
    },
    "levante-ud": {
      "primaryHex": "#B4053F",
      "secondaryHex": "#005CA5",
      "accentHex": "#FFFFFF",
      "allHex": [
        "#B4053F",
        "#005CA5",
        "#FFFFFF",
        "#DCA43E",
        "#FAC400",
        "#000000"
      ],
      "rgb": [
        "rgb(180, 5, 63)",
        "rgb(0, 92, 165)",
        "rgb(255, 255, 255)",
        "rgb(220, 164, 62)",
        "rgb(250, 196, 0)",
        "rgb(0, 0, 0)"
      ],
      "cmyk": [
        "cmyk(0%, 97%, 65%, 29%)",
        "cmyk(100%, 44%, 0%, 35%)",
        "cmyk(0%, 0%, 0%, 0%)",
        "cmyk(0%, 25%, 72%, 14%)",
        "cmyk(0%, 22%, 100%, 2%)",
        "cmyk(0%, 0%, 0%, 100%)"
      ]
    },
    "real-betis-balompie": {
      "primaryHex": "#00954C",
      "secondaryHex": "#FFFFFF",
      "accentHex": "#DE9500",
      "allHex": [
        "#00954C",
        "#FFFFFF",
        "#DE9500",
        "#D7013E"
      ],
      "rgb": [
        "rgb(0, 149, 76)",
        "rgb(255, 255, 255)",
        "rgb(222, 149, 0)",
        "rgb(215, 1, 62)"
      ],
      "cmyk": [
        "cmyk(100%, 0%, 49%, 42%)",
        "cmyk(0%, 0%, 0%, 0%)",
        "cmyk(0%, 33%, 100%, 13%)",
        "cmyk(0%, 100%, 71%, 16%)"
      ]
    },
    "real-sociedad-de-futbol": {
      "primaryHex": "#143C8B",
      "secondaryHex": "#FFFFFF",
      "accentHex": "#E6A514",
      "allHex": [
        "#143C8B",
        "#FFFFFF",
        "#E6A514",
        "#FFE24A",
        "#EC1D24",
        "#000000"
      ],
      "rgb": [
        "rgb(20, 60, 139)",
        "rgb(255, 255, 255)",
        "rgb(230, 165, 20)",
        "rgb(255, 226, 74)",
        "rgb(236, 29, 36)",
        "rgb(0, 0, 0)"
      ],
      "cmyk": [
        "cmyk(86%, 57%, 0%, 45%)",
        "cmyk(0%, 0%, 0%, 0%)",
        "cmyk(0%, 28%, 91%, 10%)",
        "cmyk(0%, 11%, 71%, 0%)",
        "cmyk(0%, 88%, 85%, 7%)",
        "cmyk(0%, 0%, 0%, 100%)"
      ]
    },
    "villarreal-cf": {
      "primaryHex": "#FFD733",
      "secondaryHex": "#EE0028",
      "accentHex": "#002D56",
      "allHex": [
        "#FFD733",
        "#EE0028",
        "#002D56",
        "#FFFFFC",
        "#FFED54",
        "#000000"
      ],
      "rgb": [
        "rgb(255, 215, 51)",
        "rgb(238, 0, 40)",
        "rgb(0, 45, 86)",
        "rgb(255, 255, 252)",
        "rgb(255, 237, 84)",
        "rgb(0, 0, 0)"
      ],
      "cmyk": [
        "cmyk(0%, 16%, 80%, 0%)",
        "cmyk(0%, 100%, 83%, 7%)",
        "cmyk(100%, 48%, 0%, 66%)",
        "cmyk(0%, 0%, 1%, 0%)",
        "cmyk(0%, 7%, 67%, 0%)",
        "cmyk(0%, 0%, 0%, 100%)"
      ]
    },
    "valencia-cf": {
      "primaryHex": "#E23C07",
      "secondaryHex": "#FFE524",
      "accentHex": "#0A0909",
      "allHex": [
        "#E23C07",
        "#FFE524",
        "#0A0909",
        "#3E93CD",
        "#FFFFFF",
        "#D69100"
      ],
      "rgb": [
        "rgb(226, 60, 7)",
        "rgb(255, 229, 36)",
        "rgb(10, 9, 9)",
        "rgb(62, 147, 205)",
        "rgb(255, 255, 255)",
        "rgb(214, 145, 0)"
      ],
      "cmyk": [
        "cmyk(0%, 73%, 97%, 11%)",
        "cmyk(0%, 10%, 86%, 0%)",
        "cmyk(0%, 10%, 10%, 96%)",
        "cmyk(70%, 28%, 0%, 20%)",
        "cmyk(0%, 0%, 0%, 0%)",
        "cmyk(0%, 32%, 100%, 16%)"
      ]
    },
    "deportivo-alaves": {
      "primaryHex": "#0232A0",
      "secondaryHex": "#FFFFFF",
      "accentHex": "#D9E0E7",
      "allHex": [
        "#0232A0",
        "#FFFFFF",
        "#D9E0E7",
        "#082E86"
      ],
      "rgb": [
        "rgb(2, 50, 160)",
        "rgb(255, 255, 255)",
        "rgb(217, 224, 231)",
        "rgb(8, 46, 134)"
      ],
      "cmyk": [
        "cmyk(99%, 69%, 0%, 37%)",
        "cmyk(0%, 0%, 0%, 0%)",
        "cmyk(6%, 3%, 0%, 9%)",
        "cmyk(94%, 66%, 0%, 47%)"
      ]
    },
    "elche-cf": {
      "primaryHex": "#C5112E",
      "secondaryHex": "#1B458F",
      "accentHex": "#E6C777",
      "allHex": [
        "#C5112E",
        "#1B458F",
        "#E6C777",
        "#866B10",
        "#FFFFFF",
        "#05642C"
      ],
      "rgb": [
        "rgb(197, 17, 46)",
        "rgb(27, 69, 143)",
        "rgb(230, 199, 119)",
        "rgb(134, 107, 16)",
        "rgb(255, 255, 255)",
        "rgb(5, 100, 44)"
      ],
      "cmyk": [
        "cmyk(0%, 91%, 77%, 23%)",
        "cmyk(81%, 52%, 0%, 44%)",
        "cmyk(0%, 13%, 48%, 10%)",
        "cmyk(0%, 20%, 88%, 47%)",
        "cmyk(0%, 0%, 0%, 0%)",
        "cmyk(95%, 0%, 56%, 61%)"
      ]
    },
    "rc-celta-de-vigo": {
      "primaryHex": "#6DACE5",
      "secondaryHex": "#D50032",
      "accentHex": "#FFFFFF",
      "allHex": [
        "#6DACE5",
        "#D50032",
        "#FFFFFF",
        "#B19221"
      ],
      "rgb": [
        "rgb(109, 172, 229)",
        "rgb(213, 0, 50)",
        "rgb(255, 255, 255)",
        "rgb(177, 146, 33)"
      ],
      "cmyk": [
        "cmyk(52%, 25%, 0%, 10%)",
        "cmyk(0%, 100%, 77%, 16%)",
        "cmyk(0%, 0%, 0%, 0%)",
        "cmyk(0%, 18%, 81%, 31%)"
      ]
    },
    "1-fc-koln": {
      "primaryHex": "#E20613",
      "secondaryHex": "#FFFFFF",
      "accentHex": "#1D1D1B",
      "allHex": [
        "#E20613",
        "#FFFFFF",
        "#1D1D1B"
      ],
      "rgb": [
        "rgb(226, 6, 19)",
        "rgb(255, 255, 255)",
        "rgb(29, 29, 27)"
      ],
      "cmyk": [
        "cmyk(0%, 97%, 92%, 11%)",
        "cmyk(0%, 0%, 0%, 0%)",
        "cmyk(0%, 0%, 7%, 89%)"
      ]
    },
    "bayer-04-leverkusen": {
      "primaryHex": "#FF0000",
      "secondaryHex": "#FFFF00",
      "accentHex": "#FFFFFF",
      "allHex": [
        "#FF0000",
        "#FFFF00",
        "#FFFFFF",
        "#000000"
      ],
      "rgb": [
        "rgb(255, 0, 0)",
        "rgb(255, 255, 0)",
        "rgb(255, 255, 255)",
        "rgb(0, 0, 0)"
      ],
      "cmyk": [
        "cmyk(0%, 100%, 100%, 0%)",
        "cmyk(0%, 0%, 100%, 0%)",
        "cmyk(0%, 0%, 0%, 0%)",
        "cmyk(0%, 0%, 0%, 100%)"
      ]
    },
    "borussia-dortmund": {
      "primaryHex": "#FFD900",
      "secondaryHex": "#000000",
      "accentHex": null,
      "allHex": [
        "#FFD900",
        "#000000"
      ],
      "rgb": [
        "rgb(255, 217, 0)",
        "rgb(0, 0, 0)"
      ],
      "cmyk": [
        "cmyk(0%, 15%, 100%, 0%)",
        "cmyk(0%, 0%, 0%, 100%)"
      ]
    },
    "fc-bayern-munchen": {
      "primaryHex": "#ED0038",
      "secondaryHex": "#286CFD",
      "accentHex": "#FFFFFF",
      "allHex": [
        "#ED0038",
        "#286CFD",
        "#FFFFFF"
      ],
      "rgb": [
        "rgb(237, 0, 56)",
        "rgb(40, 108, 253)",
        "rgb(255, 255, 255)"
      ],
      "cmyk": [
        "cmyk(0%, 100%, 76%, 7%)",
        "cmyk(84%, 57%, 0%, 1%)",
        "cmyk(0%, 0%, 0%, 0%)"
      ]
    },
    "hamburger-sv": {
      "primaryHex": "#1E5CB3",
      "secondaryHex": "#FFFFFF",
      "accentHex": "#231F20",
      "allHex": [
        "#1E5CB3",
        "#FFFFFF",
        "#231F20"
      ],
      "rgb": [
        "rgb(30, 92, 179)",
        "rgb(255, 255, 255)",
        "rgb(35, 31, 32)"
      ],
      "cmyk": [
        "cmyk(83%, 49%, 0%, 30%)",
        "cmyk(0%, 0%, 0%, 0%)",
        "cmyk(0%, 11%, 9%, 86%)"
      ]
    },
    "vfb-stuttgart": {
      "primaryHex": "#D40723",
      "secondaryHex": "#FFDC00",
      "accentHex": "#FFFFFF",
      "allHex": [
        "#D40723",
        "#FFDC00",
        "#FFFFFF",
        "#000000"
      ],
      "rgb": [
        "rgb(212, 7, 35)",
        "rgb(255, 220, 0)",
        "rgb(255, 255, 255)",
        "rgb(0, 0, 0)"
      ],
      "cmyk": [
        "cmyk(0%, 97%, 83%, 17%)",
        "cmyk(0%, 14%, 100%, 0%)",
        "cmyk(0%, 0%, 0%, 0%)",
        "cmyk(0%, 0%, 0%, 100%)"
      ]
    },
    "sv-werder-bremen": {
      "primaryHex": "#1D9053",
      "secondaryHex": "#FFFFFF",
      "accentHex": null,
      "allHex": [
        "#1D9053",
        "#FFFFFF"
      ],
      "rgb": [
        "rgb(29, 144, 83)",
        "rgb(255, 255, 255)"
      ],
      "cmyk": [
        "cmyk(80%, 0%, 42%, 44%)",
        "cmyk(0%, 0%, 0%, 0%)"
      ]
    },
    "1-fsv-mainz-05": {
      "primaryHex": "#AE0F0A",
      "secondaryHex": "#FFFFFF",
      "accentHex": null,
      "allHex": [
        "#AE0F0A",
        "#FFFFFF"
      ],
      "rgb": [
        "rgb(174, 15, 10)",
        "rgb(255, 255, 255)"
      ],
      "cmyk": [
        "cmyk(0%, 91%, 94%, 32%)",
        "cmyk(0%, 0%, 0%, 0%)"
      ]
    },
    "fc-augsburg": {
      "primaryHex": "#BA3733",
      "secondaryHex": "#FFFFFF",
      "accentHex": "#FFD42E",
      "allHex": [
        "#BA3733",
        "#FFFFFF",
        "#FFD42E",
        "#46714D",
        "#000000"
      ],
      "rgb": [
        "rgb(186, 55, 51)",
        "rgb(255, 255, 255)",
        "rgb(255, 212, 46)",
        "rgb(70, 113, 77)",
        "rgb(34, 31, 31)"
      ],
      "cmyk": [
        "cmyk(0%, 70%, 73%, 27%)",
        "cmyk(0%, 0%, 0%, 0%)",
        "cmyk(0%, 17%, 82%, 0%)",
        "cmyk(38%, 0%, 32%, 56%)",
        "cmyk(0%, 9%, 9%, 87%)"
      ]
    },
    "sc-freiburg": {
      "primaryHex": "#000000",
      "secondaryHex": "#FFFFFF",
      "accentHex": null,
      "allHex": [
        "#000000",
        "#FFFFFF"
      ],
      "rgb": [
        "rgb(0, 0, 0)",
        "rgb(255, 255, 255)"
      ],
      "cmyk": [
        "cmyk(0%, 0%, 0%, 100%)",
        "cmyk(0%, 0%, 0%, 0%)"
      ]
    },
    "borussia-monchengladbach": {
      "primaryHex": "#000000",
      "secondaryHex": "#FFFFFF",
      "accentHex": null,
      "allHex": [
        "#000000",
        "#FFFFFF"
      ],
      "rgb": [
        "rgb(0, 0, 0)",
        "rgb(255, 255, 255)"
      ],
      "cmyk": [
        "cmyk(0%, 0%, 0%, 100%)",
        "cmyk(0%, 0%, 0%, 0%)"
      ]
    },
    "eintracht-frankfurt": {
      "primaryHex": "#E1020C",
      "secondaryHex": "#FFFFFF",
      "accentHex": null,
      "allHex": [
        "#E1020C",
        "#FFFFFF"
      ],
      "rgb": [
        "rgb(225, 2, 12)",
        "rgb(255, 255, 255)"
      ],
      "cmyk": [
        "cmyk(0%, 99%, 95%, 12%)",
        "cmyk(0%, 0%, 0%, 0%)"
      ]
    },
    "1-fc-union-berlin": {
      "primaryHex": "#E30613",
      "secondaryHex": "#FFDD00",
      "accentHex": "#FFFFFF",
      "allHex": [
        "#E30613",
        "#FFDD00",
        "#FFFFFF",
        "#000000"
      ],
      "rgb": [
        "rgb(227, 6, 19)",
        "rgb(255, 221, 0)",
        "rgb(255, 255, 255)",
        "rgb(0, 0, 0)"
      ],
      "cmyk": [
        "cmyk(0%, 97%, 92%, 11%)",
        "cmyk(0%, 13%, 100%, 0%)",
        "cmyk(0%, 0%, 0%, 0%)",
        "cmyk(0%, 0%, 0%, 100%)"
      ]
    },
    "rb-leipzig": {
      "primaryHex": "#DD0741",
      "secondaryHex": "#FFFFFF",
      "accentHex": "#001F47",
      "allHex": [
        "#DD0741",
        "#FFFFFF",
        "#001F47",
        "#DADADA"
      ],
      "rgb": [
        "rgb(221, 7, 65)",
        "rgb(255, 255, 255)",
        "rgb(0, 31, 71)",
        "rgb(218, 218, 218)"
      ],
      "cmyk": [
        "cmyk(0%, 97%, 71%, 13%)",
        "cmyk(0%, 0%, 0%, 0%)",
        "cmyk(100%, 56%, 0%, 72%)",
        "cmyk(0%, 0%, 0%, 15%)"
      ]
    },
    "fluminense-fc": {
      "primaryHex": "#92062A",
      "secondaryHex": "#006039",
      "accentHex": "#FFFFFF",
      "allHex": [
        "#92062A",
        "#006039",
        "#FFFFFF"
      ],
      "rgb": [
        "rgb(146, 6, 42)",
        "rgb(0, 96, 57)",
        "rgb(255, 255, 255)"
      ],
      "cmyk": [
        "cmyk(0%, 96%, 71%, 43%)",
        "cmyk(100%, 0%, 41%, 62%)",
        "cmyk(0%, 0%, 0%, 0%)"
      ]
    },
    "gremio-fbpa": {
      "primaryHex": "#0D80BF",
      "secondaryHex": "#1F1A17",
      "accentHex": "#FFFFFF",
      "allHex": [
        "#0D80BF",
        "#1F1A17",
        "#FFFFFF",
        "#ABAAAA",
        "#93754F",
        "#F8C300"
      ],
      "rgb": [
        "rgb(13, 128, 191)",
        "rgb(31, 26, 23)",
        "rgb(255, 255, 255)",
        "rgb(171, 170, 170)",
        "rgb(147, 117, 79)",
        "rgb(248, 195, 0)"
      ],
      "cmyk": [
        "cmyk(93%, 33%, 0%, 25%)",
        "cmyk(0%, 16%, 26%, 88%)",
        "cmyk(0%, 0%, 0%, 0%)",
        "cmyk(0%, 1%, 1%, 33%)",
        "cmyk(0%, 20%, 46%, 42%)",
        "cmyk(0%, 21%, 100%, 3%)"
      ]
    },
    "se-palmeiras": {
      "primaryHex": "#006437",
      "secondaryHex": "#FFFFFF",
      "accentHex": null,
      "allHex": [
        "#006437",
        "#FFFFFF"
      ],
      "rgb": [
        "rgb(0, 100, 55)",
        "rgb(255, 255, 255)"
      ],
      "cmyk": [
        "cmyk(100%, 0%, 45%, 61%)",
        "cmyk(0%, 0%, 0%, 0%)"
      ]
    },
    "botafogo-fr": {
      "primaryHex": "#000000",
      "secondaryHex": "#FFFFFF",
      "accentHex": null,
      "allHex": [
        "#000000",
        "#FFFFFF"
      ],
      "rgb": [
        "rgb(0, 0, 0)",
        "rgb(255, 255, 255)"
      ],
      "cmyk": [
        "cmyk(0%, 0%, 0%, 100%)",
        "cmyk(0%, 0%, 0%, 0%)"
      ]
    },
    "cruzeiro-ec": {
      "primaryHex": "#2F529E",
      "secondaryHex": "#FEFEFE",
      "accentHex": null,
      "allHex": [
        "#2F529E",
        "#FEFEFE"
      ],
      "rgb": [
        "rgb(47, 82, 158)",
        "rgb(254, 254, 254)"
      ],
      "cmyk": [
        "cmyk(70%, 48%, 0%, 38%)",
        "cmyk(0%, 0%, 0%, 0%)"
      ]
    },
    "ec-bahia": {
      "primaryHex": "#006CB5",
      "secondaryHex": "#ED3237",
      "accentHex": "#FEFEFE",
      "allHex": [
        "#006CB5",
        "#ED3237",
        "#FEFEFE",
        "#FEDD22"
      ],
      "rgb": [
        "rgb(0, 108, 181)",
        "rgb(237, 50, 55)",
        "rgb(254, 254, 254)",
        "rgb(254, 221, 34)"
      ],
      "cmyk": [
        "cmyk(100%, 40%, 0%, 29%)",
        "cmyk(0%, 79%, 77%, 7%)",
        "cmyk(0%, 0%, 0%, 0%)",
        "cmyk(0%, 13%, 87%, 0%)"
      ]
    },
    "sc-corinthians-paulista": {
      "primaryHex": "#ED1C2E",
      "secondaryHex": "#FFFFFF",
      "accentHex": "#231F20",
      "allHex": [
        "#ED1C2E",
        "#FFFFFF",
        "#231F20"
      ],
      "rgb": [
        "rgb(237, 28, 46)",
        "rgb(255, 255, 255)",
        "rgb(35, 31, 32)"
      ],
      "cmyk": [
        "cmyk(0%, 88%, 81%, 7%)",
        "cmyk(0%, 0%, 0%, 0%)",
        "cmyk(0%, 11%, 9%, 86%)"
      ]
    },
    "ec-vitoria": {
      "primaryHex": "#FF1100",
      "secondaryHex": "#000000",
      "accentHex": "#FFFFFF",
      "allHex": [
        "#FF1100",
        "#000000",
        "#FFFFFF"
      ],
      "rgb": [
        "rgb(255, 17, 0)",
        "rgb(0, 0, 0)",
        "rgb(255, 255, 255)"
      ],
      "cmyk": [
        "cmyk(0%, 93%, 100%, 0%)",
        "cmyk(0%, 0%, 0%, 100%)",
        "cmyk(0%, 0%, 0%, 0%)"
      ]
    },
    "coritiba-fbc": {
      "primaryHex": "#005742",
      "secondaryHex": "#FFFFFF",
      "accentHex": "#FAD716",
      "allHex": [
        "#005742",
        "#FFFFFF",
        "#FAD716"
      ],
      "rgb": [
        "rgb(0, 87, 66)",
        "rgb(255, 255, 255)",
        "rgb(250, 215, 22)"
      ],
      "cmyk": [
        "cmyk(100%, 0%, 24%, 66%)",
        "cmyk(0%, 0%, 0%, 0%)",
        "cmyk(0%, 14%, 91%, 2%)"
      ]
    },
    "rb-bragantino": {
      "primaryHex": "#D2003C",
      "secondaryHex": "#FFCC00",
      "accentHex": "#FFFFFF",
      "allHex": [
        "#D2003C",
        "#FFCC00",
        "#FFFFFF",
        "#001D46",
        "#DADADA"
      ],
      "rgb": [
        "rgb(210, 0, 60)",
        "rgb(255, 204, 0)",
        "rgb(255, 255, 255)",
        "rgb(0, 29, 70)",
        "rgb(218, 218, 218)"
      ],
      "cmyk": [
        "cmyk(0%, 100%, 71%, 18%)",
        "cmyk(0%, 20%, 100%, 0%)",
        "cmyk(0%, 0%, 0%, 0%)",
        "cmyk(100%, 59%, 0%, 73%)",
        "cmyk(0%, 0%, 0%, 15%)"
      ]
    },
    "mirassol-fc": {
      "primaryHex": "#EEED05",
      "secondaryHex": "#256C38",
      "accentHex": "#FFFFFF",
      "allHex": [
        "#EEED05",
        "#256C38",
        "#FFFFFF"
      ],
      "rgb": [
        "rgb(238, 237, 5)",
        "rgb(37, 108, 56)",
        "rgb(255, 255, 255)"
      ],
      "cmyk": [
        "cmyk(0%, 0%, 98%, 7%)",
        "cmyk(66%, 0%, 48%, 58%)",
        "cmyk(0%, 0%, 0%, 0%)"
      ]
    },
    "sc-internacional": {
      "primaryHex": "#E5050F",
      "secondaryHex": "#FFFFFF",
      "accentHex": null,
      "allHex": [
        "#E5050F",
        "#FFFFFF"
      ],
      "rgb": [
        "rgb(229, 5, 15)",
        "rgb(255, 255, 255)"
      ],
      "cmyk": [
        "cmyk(0%, 98%, 93%, 10%)",
        "cmyk(0%, 0%, 0%, 0%)"
      ]
    },
    "santos-fc": {
      "primaryHex": "#000000",
      "secondaryHex": "#FFFFFF",
      "accentHex": "#FFCC11",
      "allHex": [
        "#000000",
        "#FFFFFF",
        "#FFCC11"
      ],
      "rgb": [
        "rgb(0, 0, 0)",
        "rgb(255, 255, 255)",
        "rgb(255, 204, 17)"
      ],
      "cmyk": [
        "cmyk(0%, 0%, 0%, 100%)",
        "cmyk(0%, 0%, 0%, 0%)",
        "cmyk(0%, 20%, 93%, 0%)"
      ]
    }
  }
}
